{"clips":[{"ch":1,"id":1,"start":0,"stop":1693439},{"ch":2,"id":2,"start":0,"stop":564480},{"ch":2,"id":3,"start":564480,"stop":1128960},{"ch":2,"id":4,"start":1128960,"stop":1693440},{"ch":3,"id":5,"start":0,"stop":1693439},{"ch":3,"id":7,"start":1693439,"stop":3386878},{"ch":2,"id":9,"start":1693440,"stop":3386879},{"ch":0,"id":8,"start":3386944,"stop":3430528},{"ch":0,"id":10,"start":3386880,"stop":3386944},{"ch":0,"id":0,"start":0,"stop":1693440},{"ch":0,"id":6,"start":1693440,"stop":3386880}],"loop":true,"loop_in":1693440,"loop_out":3386880,"mixer_params":[1.0,1.0,1.0,1.0,0.0,0.0,0.0,0.0],"pos":1761792,"tape_type":1,"tempobpmdecimal":750,"tempometronomelevel":0.0,"tempometronometype":0,"temposyncout":1,"temposynctype":0,"track":0}
