{"clips":[{"ch":0,"id":0,"start":333354,"stop":377312},{"ch":0,"id":1,"start":0,"stop":333354},{"ch":1,"id":3,"start":0,"stop":373568},{"ch":0,"id":2,"start":416660,"stop":750047},{"ch":0,"id":4,"start":750047,"stop":1083401},{"ch":0,"id":5,"start":1083401,"stop":1416756},{"ch":0,"id":6,"start":1416756,"stop":1750110},{"ch":0,"id":7,"start":1750110,"stop":2144990},{"ch":1,"id":8,"start":416660,"stop":2083463},{"ch":3,"id":11,"start":416692,"stop":2083464},{"ch":2,"id":12,"start":416692,"stop":2083464},{"ch":3,"id":13,"start":5250328,"stop":5439678},{"ch":3,"id":14,"start":2250110,"stop":5250328},{"ch":0,"id":15,"start":2333480,"stop":5166988},{"ch":1,"id":16,"start":2333480,"stop":5166988},{"ch":2,"id":10,"start":5583682,"stop":7250486},{"ch":1,"id":9,"start":5500343,"stop":6154423},{"ch":2,"id":17,"start":2333448,"stop":2333480},{"ch":2,"id":18,"start":2333480,"stop":5166988}],"loop":true,"loop_in":3333544,"loop_out":5000316,"mixer_params":[0.50949096880,0.60946656250,0.559509250,0.72949218750,0.0,0.0,-0.0156250,0.0],"pos":3833575,"tape_type":0,"tempobpmdecimal":1270,"tempometronomelevel":0.0,"tempometronometype":0,"temposyncout":1,"temposynctype":0,"track":3}
